psmanager/__init__.py
psmanager/pchecker.py
psmanager/pgenerator.py
psmanager-0.0.1.dist-info/LICENSE
psmanager-0.0.1.dist-info/METADATA
psmanager-0.0.1.dist-info/WHEEL
psmanager-0.0.1.dist-info/top_level.txt
psmanager-0.0.1.dist-info/RECORD
