Metadata-Version: 2.1
Name: psmanager
Version: 0.0.1
Summary: psmanager(Password Manager) is a python package which helps managing passwords
Home-page: https://github.com/saaemfairdi07/psmanager/
Author: Saaem Faridi
Author-email: <officialsaaem@gmail.com>
License: MIT
Classifier: License :: OSI Approved :: MIT License
Classifier: Programming Language :: Python :: 3
Classifier: Operating System :: Unix
Classifier: Operating System :: MacOS :: MacOS X
Classifier: Operating System :: Microsoft :: Windows
License-File: LICENSE
